flask_resource_chassis/__init__.py
flask_resource_chassis/exceptions.py
flask_resource_chassis/schemas.py
flask_resource_chassis/services.py
flask_resource_chassis/utils.py
oauth_client/__init__.py
flask_resource_chassis-1.0.2.dist-info/METADATA
flask_resource_chassis-1.0.2.dist-info/WHEEL
flask_resource_chassis-1.0.2.dist-info/top_level.txt
flask_resource_chassis-1.0.2.dist-info/RECORD
