Metadata-Version: 2.1
Name: flask-resource-chassis
Version: 1.0.2
Summary: Extends flask restful functionality
Home-page: UNKNOWN
Author: UNKNOWN
Author-email: UNKNOWN
License: UNKNOWN
Platform: UNKNOWN
